[
    {
        "id": 1,
        "marca": "teste1",
        "modelo": "teste2",
        "cor": "teste3",
        "ano": "teste4"
    },
    {
        "id": 2,
        "marca": "dsdsds",
        "modelo": "teste2",
        "cor": "teste3",
        "ano": "teste4"
    },
    {
        "id": 3,
        "marca": "a",
        "modelo": "b",
        "cor": "c",
        "ano": "d"
    },
    {
        "id": 4,
        "marca": "g",
        "modelo": "h",
        "cor": "f",
        "ano": "d"
    },
    {
        "id": 5,
        "marca": "seila",
        "modelo": "t",
        "cor": "q",
        "ano": "s"
    }
]